<?xml version="1.0" encoding="utf-8" ?>
<dwsync>
<file name="gdthumb.php" server="ftp.irohanipopeto.com" local="130898888419285212" remote="131176167600000000" />
<file name="Mail.php" server="ftp.irohanipopeto.com" local="131146712536526033" remote="131176167600000000" />
<file name="MDB2.php" server="ftp.irohanipopeto.com" local="131146842808161012" remote="131176167600000000" />
<file name="PEAR.php" server="ftp.irohanipopeto.com" local="130898888417255096" remote="131176167600000000" />
<file name="PEAR5.php" server="ftp.irohanipopeto.com" local="130898888417255096" remote="131176167600000000" />
<file name="Request.php" server="ftp.irohanipopeto.com" local="130898888417265096" remote="131176167600000000" />
<file name="SearchReplace.php" server="ftp.irohanipopeto.com" local="130898888417435106" remote="131176167600000000" />
<file name="Tar.php" server="ftp.irohanipopeto.com" local="130898888418275154" remote="131176167600000000" />
</dwsync>